{
  "plugin_manager_url": "http://github.com/bombsquad-community/plugin-manager/{content_type}/{tag}/plugin_manager.py",
  "versions": {
    "0.1.4": {
       "api_version": 7,
       "commit_sha": "9366f2c0",
       "released_on": "28-08-2022",
       "md5sum": "25f380296ddd564c7ed227abb8b35513"
    }
  },
  "categories": [
    "http://github.com/bombsquad-community/plugin-manager/{content_type}/{tag}/plugins/utilities.json",
    "http://github.com/bombsquad-community/plugin-manager/{content_type}/{tag}/plugins/minigames.json",
    "http://github.com/bombsquad-community/plugin-manager/{content_type}/{tag}/plugins/maps.json"
  ],
  "external_source_url": "http://github.com/{repository}/{content_type}/{tag}/category.json"
}
